LICENSE
README.md
pyclasses.py
setup.py
pyclasses.egg-info/PKG-INFO
pyclasses.egg-info/SOURCES.txt
pyclasses.egg-info/dependency_links.txt
pyclasses.egg-info/entry_points.txt
pyclasses.egg-info/requires.txt
pyclasses.egg-info/top_level.txt