Metadata-Version: 2.1
Name: pyclasses
Version: 0.4
License-File: LICENSE
Requires-Dist: pydot
Requires-Dist: setuptools
